abjad/__init__.py
abjad/_contributions.py
abjad/_getlib.py
abjad/_indentlib.py
abjad/_iterlib.py
abjad/_updatelib.py
abjad/_version.py
abjad/bind.py
abjad/configuration.py
abjad/contextmanagers.py
abjad/cyclictuple.py
abjad/deprecated.py
abjad/duration.py
abjad/enumerate.py
abjad/enums.py
abjad/exceptions.py
abjad/format.py
abjad/get.py
abjad/grace_corner_cases.py
abjad/illustrators.py
abjad/indicators.py
abjad/instruments.py
abjad/io.py
abjad/iterate.py
abjad/iterpitches.py
abjad/label.py
abjad/lilypondfile.py
abjad/lyconst.py
abjad/lyenv.py
abjad/makers.py
abjad/math.py
abjad/meter.py
abjad/metricmodulation.py
abjad/mutate.py
abjad/obgc.py
abjad/overrides.py
abjad/parentage.py
abjad/pattern.py
abjad/pcollections.py
abjad/persist.py
abjad/pitch.py
abjad/py.typed
abjad/rhythmtrees.py
abjad/score.py
abjad/select.py
abjad/sequence.py
abjad/setclass.py
abjad/spanners.py
abjad/string.py
abjad/tag.py
abjad/timespan.py
abjad/tweaks.py
abjad/verticalmoment.py
abjad/wf.py
abjad/wrapper.py
abjad/ext/__init__.py
abjad/ext/sphinx.py
abjad/parsers/__init__.py
abjad/parsers/base.py
abjad/parsers/parse.py
abjad/parsers/parser.py
abjad/parsers/reduced.py
abjad/parsers/scheme.py
abjad/scm/abjad-coloring.ily
abjad/scm/abjad-hairpins.ily
abjad/scm/abjad-make-music-functions.ily
abjad/scm/abjad-metric-modulations.ily
abjad/scm/abjad-metronome-marks.ily
abjad/scm/abjad-spanners.ily
abjad/scm/abjad-text-spanner-line-styles.ily
abjad/scm/abjad.ily
abjad/scm/all-edo-markups-example.ily
abjad/scm/default-et-accidental-markups.ily
abjad/scm/ekmelos-edo-accidental-markups.ily
abjad/scm/ekmelos-ji-accidental-markups.ily
abjad/scm/fraction-accidental-markups.ily
abjad/scm/general-et-accidental-markups.ily
abjad/scm/harmonic-series-layout.ily
abjad/scm/heji2-ji-accidental-markups.ily
abjad/scm/markup-functions.ily
abjad/scm/nalesnik-slash.ily
abjad/scm/nalesnik-text-spanner-id.ily
abjad-3.29.dist-info/licenses/LICENSE
abjad-3.29.dist-info/METADATA
abjad-3.29.dist-info/WHEEL
abjad-3.29.dist-info/top_level.txt
abjad-3.29.dist-info/RECORD
