Metadata-Version: 2.4
Name: abjad
Version: 3.29
Summary: Abjad is a Python API for building LilyPond files.
Author-email: Trevor Bača <trevor.baca@gmail.com>, Joséphine Wolf Oberholtzer <josephine.wolf.oberholtzer@gmail.com>
License: MIT
Project-URL: Homepage, https://abjad.github.io
Keywords: lilypond,music composition,music notation
Classifier: Development Status :: 5 - Production/Stable
Classifier: License :: OSI Approved :: GNU General Public License (GPL)
Classifier: Programming Language :: Python :: 3.12
Classifier: Programming Language :: Python :: 3.13
Classifier: Topic :: Artistic Software
Requires-Python: >=3.12
License-File: LICENSE
Requires-Dist: ply>=3.11
Requires-Dist: roman>=5.0
Requires-Dist: uqbar>=0.7.4
Provides-Extra: dev
Requires-Dist: black==25.1.0; extra == "dev"
Requires-Dist: build==1.2.2.post1; extra == "dev"
Requires-Dist: flake8==7.2.0; extra == "dev"
Requires-Dist: isort==6.0.1; extra == "dev"
Requires-Dist: mypy==1.15.0; extra == "dev"
Requires-Dist: pytest==8.3.5; extra == "dev"
Requires-Dist: pytest-cov==6.1.1; extra == "dev"
Requires-Dist: pytest-helpers-namespace==2021.12.29; extra == "dev"
Requires-Dist: setuptools==80.0.0; extra == "dev"
Requires-Dist: sphinx==8.1.3; extra == "dev"
Requires-Dist: sphinx-rtd-theme==3.0.2; extra == "dev"
Requires-Dist: sphinx-toggleprompt==0.6.0; extra == "dev"
Requires-Dist: twine==6.1.0; extra == "dev"
Dynamic: license-file
